LICENSE
README.md
setup.py
botpgsql/__init__.py
botpgsql/app.py
botpgsql/app_v0.py
botpgsql/database.py
botpgsql/decorators.py
botpgsql/exceptions.py
botpgsql.egg-info/PKG-INFO
botpgsql.egg-info/SOURCES.txt
botpgsql.egg-info/dependency_links.txt
botpgsql.egg-info/requires.txt
botpgsql.egg-info/top_level.txt