Metadata-Version: 2.1
Name: botpgsql
Version: 0.3.0
Summary: Class to build database relationship for RPA
Home-page: https://github.com/botlorien/botpgsql
Author: Ben-Hur P. B. Santos
Author-email: botlorien@gmail.com
Classifier: Programming Language :: Python :: 3
Classifier: License :: OSI Approved :: MIT License
Classifier: Operating System :: OS Independent
Requires-Python: >=3.10
License-File: LICENSE
Requires-Dist: psycopg2-binary
Requires-Dist: pandas
Requires-Dist: botapp
